aesim/simba/__init__.py
aesim/simba/__init__.pyi
aesim/simba/Resources/CommunityToolkit.Mvvm.dll
aesim/simba/Resources/DeviceId.Linux.dll
aesim/simba/Resources/DeviceId.Mac.dll
aesim/simba/Resources/DeviceId.Windows.dll
aesim/simba/Resources/DeviceId.dll
aesim/simba/Resources/Google.OrTools.dll
aesim/simba/Resources/Google.Protobuf.dll
aesim/simba/Resources/Python.Runtime.dll
aesim/simba/Resources/Simba.Data.deps.json
aesim/simba/Resources/Simba.Data.dll
aesim/simba/Resources/Simba.Data.runtimeconfig.json
aesim/simba/Resources/Simba.Drawing.dll
aesim/simba/Resources/Simba.Helper.dll
aesim/simba/Resources/Simba.SvgCanvas.dll
aesim/simba/Resources/Resources/DesignExamples.jsimba
aesim/simba/Resources/Resources/PsimSimbaDictionary.json
aesim/simba/Resources/Resources/libSimba.Solvers.linux-arm64.so
aesim/simba/Resources/Resources/simba_library.c
aesim/simba/Resources/Resources/simba_library.h
aesim/simba/Resources/Resources/Examples/acdc_3ph_diodebridge.jsimba
aesim/simba/Resources/Resources/Examples/acdc_3ph_thyristor_rectifier.jsimba
aesim/simba/Resources/Resources/Examples/acdc_pfc_totem_pole.jsimba
aesim/simba/Resources/Resources/Examples/bldc_drive_example.jsimba
aesim/simba/Resources/Resources/Examples/dcac_3_phase_inverter_spwm.jsimba
aesim/simba/Resources/Resources/Examples/dcac_5lvl_npc.jsimba
aesim/simba/Resources/Resources/Examples/dcdc_boost_converter.jsimba
aesim/simba/Resources/Resources/Examples/dcdc_buck_c_code.jsimba
aesim/simba/Resources/Resources/Examples/dcdc_buck_chopper_thermal.jsimba
aesim/simba/Resources/Resources/Examples/dcdc_buck_converter_ac_sweep.jsimba
aesim/simba/Resources/Resources/Examples/dcdc_buck_detailed.jsimba
aesim/simba/Resources/Resources/Examples/dcdc_buckboost.jsimba
aesim/simba/Resources/Resources/Examples/dcdc_dual_active_bridge_converter.jsimba
aesim/simba/Resources/Resources/Examples/dcdc_flyback.jsimba
aesim/simba/Resources/Resources/Examples/dcdc_forward.jsimba
aesim_simba-2025.11.15.dist-info/METADATA
aesim_simba-2025.11.15.dist-info/WHEEL
aesim_simba-2025.11.15.dist-info/top_level.txt
aesim_simba-2025.11.15.dist-info/RECORD
