Metadata-Version: 2.4
Name: aesim.simba
Version: 2025.11.15
Summary: Power Electronics and Motor Drive Simulation
Home-page: https://simba.io
Author: AESIM.tech
Author-email: contact@aesim.tech
License: By using aesim.simba, you agree to the license agreement available here: https://www.simba.io/static/EULA.pdf
Classifier: Programming Language :: Python :: 3.8
Classifier: Programming Language :: Python :: 3.9
Classifier: Programming Language :: Python :: 3.10
Classifier: Programming Language :: Python :: 3.11
Classifier: Programming Language :: Python :: 3.12
Classifier: Programming Language :: Python :: 3.13
Requires-Python: >=3.8
Requires-Dist: pythonnet>=3.0.5
Dynamic: author
Dynamic: author-email
Dynamic: classifier
Dynamic: description
Dynamic: description-content-type
Dynamic: home-page
Dynamic: license
Dynamic: requires-dist
Dynamic: requires-python
Dynamic: summary
